__init__.py
ailitellm/__init__.py
ailitellm/_ai_operations.py
ailitellm/_ai_validator.py
ailitellm/_const.py
ailitellm/_main.py
ailitellm/_types.py
ailitellm/_unified_ai_api_server.py
ailitellm/_serve_models/__init__.py
ailitellm/_serve_models/_ollama_api.py
ailitellm/_serve_models/_openai_style.py
ailitellm/tools/__init__.py
ailitellm/tools/_gitingest.py
ailitellm-0.1.10.dist-info/LICENSE
ailitellm-0.1.10.dist-info/METADATA
ailitellm-0.1.10.dist-info/WHEEL
ailitellm-0.1.10.dist-info/top_level.txt
ailitellm-0.1.10.dist-info/RECORD
